dsock/__init__.py
dsock/channel.py
dsock/pipe.py
dsock/protocol.py
dsock/socket.py
dsock/transport.py
dsock-0.5.dist-info/COPYING
dsock-0.5.dist-info/METADATA
dsock-0.5.dist-info/WHEEL
dsock-0.5.dist-info/top_level.txt
dsock-0.5.dist-info/RECORD
