Metadata-Version: 2.1
Name: dsock
Version: 0.5
Summary: File-based socket server
Home-page: https://git.bobc.io/bobc/dsock
Author: Bob Carroll
Author-email: bob.carroll@alum.rit.edu
Classifier: Development Status :: 4 - Beta
Classifier: Environment :: Console
Classifier: Environment :: No Input/Output (Daemon)
Classifier: Framework :: AsyncIO
Classifier: Intended Audience :: Developers
Classifier: Intended Audience :: End Users/Desktop
Classifier: License :: OSI Approved :: GNU General Public License v2 (GPLv2)
Classifier: Operating System :: MacOS :: MacOS X
Classifier: Operating System :: Microsoft :: Windows
Classifier: Operating System :: POSIX :: Linux
Classifier: Programming Language :: Python :: 3
Classifier: Topic :: System :: Networking
License-File: COPYING
